profiler/__init__.py
profiler/core.py
profiler/custom_tracer.py
profiler/logger.py
profiler/profiler_output_pb2.py
profiler/profiler_output_pb2_grpc.py
profiler/session.py
profiler/session_pb2.py
profiler/session_pb2_grpc.py
profiler/token.py
profiler/token_pb2.py
profiler/token_pb2_grpc.py
profiler/tokens_usage.py
profiler/utils.py
test/__init__.py
test/test_is_function_pure.py
test/test_profiler.py
hostasphere_profiler-1.0.dist-info/METADATA
hostasphere_profiler-1.0.dist-info/WHEEL
hostasphere_profiler-1.0.dist-info/top_level.txt
hostasphere_profiler-1.0.dist-info/RECORD
