Metadata-Version: 2.1
Name: hostasphere_profiler
Version: 1.0
Summary: Hostasphere Profiler API
Home-page: https://github.com/hand-e-fr/hostasphere
Author: William Jolivet
Author-email: william.jolivet@epitech.eu
Requires-Python: >=3.6
Requires-Dist: requests>=2.32.3
Requires-Dist: psutil>=6.0.0
Requires-Dist: grpcio>=1.66.2
Requires-Dist: grpcio-tools>=1.66.2
Requires-Dist: OpenHosta>=1.2.0
